tracbookmark/__init__.py
tracbookmark/compat.py
tracbookmark/htdocs/bookmark.png
tracbookmark/htdocs/css/tracbookmark.css
tracbookmark/htdocs/js/tracbookmark.js
tracbookmark/templates/bookmark_list.html
tracbookmark/templates/bookmark_list_jinja.html
TracBookmark-1.0.1.dist-info/COPYING
TracBookmark-1.0.1.dist-info/METADATA
TracBookmark-1.0.1.dist-info/WHEEL
TracBookmark-1.0.1.dist-info/entry_points.txt
TracBookmark-1.0.1.dist-info/top_level.txt
TracBookmark-1.0.1.dist-info/RECORD
