Metadata-Version: 2.1
Name: TracBookmark
Version: 1.0.1
Summary: A plugin to bookmark Trac resources.
Home-page: https://trac-hacks.org/wiki/BookmarkPlugin
Author: Yoshiyuki Sugimoto
Maintainer: Yoshiyuki Sugimoto
Maintainer-email: s.yosiyuki@gmail.com
License: 3-clause BSD
Platform: UNKNOWN
Classifier: Development Status :: 5 - Production/Stable
Classifier: Environment :: Plugins
Classifier: Environment :: Web Environment
Classifier: Framework :: Trac
Classifier: License :: OSI Approved :: BSD License
Classifier: Natural Language :: English
Classifier: Operating System :: OS Independent
Classifier: Programming Language :: Python :: 2
Classifier: Programming Language :: Python :: 2.7
Classifier: Programming Language :: Python :: 3
Requires-Dist: Trac
